basic_models/__init__.py
basic_models/actions.py
basic_models/managers.py
basic_models/models.py
basic_models/version.py
basic_models/admin/__init__.py
basic_models/admin/admin.py
basic_models/templates/admin/change_form_with_local_preview.html
django_basic_models-4.0.0.dist-info/LICENSE.md
django_basic_models-4.0.0.dist-info/METADATA
django_basic_models-4.0.0.dist-info/WHEEL
django_basic_models-4.0.0.dist-info/top_level.txt
django_basic_models-4.0.0.dist-info/RECORD
